README.md
setup.py
cobastem/Stem.py
cobastem/__init__.py
cobastem.egg-info/PKG-INFO
cobastem.egg-info/SOURCES.txt
cobastem.egg-info/dependency_links.txt
cobastem.egg-info/top_level.txt