Metadata-Version: 2.1
Name: cobastem
Version: 1.0.1
Summary: Library for stemming Madurese text
